wx/__init__.py
wx/__version__.py
wx/_adv.cp314-win_amd64.pyd
wx/_aui.cp314-win_amd64.pyd
wx/_core.cp314-win_amd64.pyd
wx/_dataview.cp314-win_amd64.pyd
wx/_glcanvas.cp314-win_amd64.pyd
wx/_grid.cp314-win_amd64.pyd
wx/_html.cp314-win_amd64.pyd
wx/_html2.cp314-win_amd64.pyd
wx/_media.cp314-win_amd64.pyd
wx/_msw.cp314-win_amd64.pyd
wx/_propgrid.cp314-win_amd64.pyd
wx/_ribbon.cp314-win_amd64.pyd
wx/_richtext.cp314-win_amd64.pyd
wx/_stc.cp314-win_amd64.pyd
wx/_xml.cp314-win_amd64.pyd
wx/_xrc.cp314-win_amd64.pyd
wx/adv.py
wx/adv.pyi
wx/aui.py
wx/aui.pyi
wx/core.py
wx/core.pyi
wx/dataview.py
wx/dataview.pyi
wx/glcanvas.py
wx/glcanvas.pyi
wx/grid.py
wx/grid.pyi
wx/html.py
wx/html.pyi
wx/html2.py
wx/html2.pyi
wx/media.py
wx/media.pyi
wx/msw.py
wx/msw.pyi
wx/propgrid.py
wx/propgrid.pyi
wx/ribbon.py
wx/ribbon.pyi
wx/richtext.py
wx/richtext.pyi
wx/siplib.cp314-win_amd64.pyd
wx/stc.py
wx/stc.pyi
wx/wxbase315u_net_vc140_x64.dll
wx/wxbase315u_vc140_x64.dll
wx/wxbase315u_xml_vc140_x64.dll
wx/wxmsw315u_adv_vc140_x64.dll
wx/wxmsw315u_aui_vc140_x64.dll
wx/wxmsw315u_core_vc140_x64.dll
wx/wxmsw315u_gl_vc140_x64.dll
wx/wxmsw315u_html_vc140_x64.dll
wx/wxmsw315u_media_vc140_x64.dll
wx/wxmsw315u_propgrid_vc140_x64.dll
wx/wxmsw315u_qa_vc140_x64.dll
wx/wxmsw315u_ribbon_vc140_x64.dll
wx/wxmsw315u_richtext_vc140_x64.dll
wx/wxmsw315u_stc_vc140_x64.dll
wx/wxmsw315u_webview_vc140_x64.dll
wx/wxmsw315u_xrc_vc140_x64.dll
wx/xml.py
wx/xml.pyi
wx/xrc.py
wx/xrc.pyi
wx/demo/AUI_DockingWindowMgr.py
wx/demo/AUI_MDI.py
wx/demo/AUI_Notebook.py
wx/demo/About.py
wx/demo/AboutBox.py
wx/demo/ActiveXWrapper_Acrobat.py
wx/demo/ActiveXWrapper_IE.py
wx/demo/ActiveX_FlashWindow.py
wx/demo/ActiveX_IEHtmlWindow.py
wx/demo/ActiveX_PDFWindow.py
wx/demo/ActivityIndicator.py
wx/demo/AddPrivateFont.py
wx/demo/AdjustChannels.py
wx/demo/AlphaDrawing.py
wx/demo/AnalogClock.py
wx/demo/AnimationCtrl.py
wx/demo/ArtProvider.py
wx/demo/BannerWindow.py
wx/demo/BitmapButton.py
wx/demo/BitmapComboBox.py
wx/demo/BitmapFromBuffer.py
wxpython_zombie-3.1.5.9.dist-info/licenses/LICENSE.txt
wxpython_zombie-3.1.5.9.dist-info/METADATA
wxpython_zombie-3.1.5.9.dist-info/WHEEL
wxpython_zombie-3.1.5.9.dist-info/entry_points.txt
wxpython_zombie-3.1.5.9.dist-info/top_level.txt
wxpython_zombie-3.1.5.9.dist-info/RECORD
