Metadata-Version: 2.4
Name: wxPython-zombie
Version: 3.1.5.9
Summary: Cross platform GUI toolkit for Python, 'Zombie' version
Maintainer: Stephan Zevenhuizen
Maintainer-email: S.J.M.Zevenhuizen@uu.nl
License: wxWindows
Keywords: GUI,wx,wxWindows,wxWidgets,wxPython,zombie
Platform: win-amd64
Platform: linux-x86_64
Classifier: Development Status :: 6 - Mature
Classifier: Environment :: Win32 (MS Windows)
Classifier: Environment :: X11 Applications :: GTK
Classifier: Intended Audience :: Developers
Classifier: License :: OSI Approved
Classifier: Operating System :: Microsoft :: Windows :: Windows 10
Classifier: Operating System :: Microsoft :: Windows :: Windows 11
Classifier: Operating System :: POSIX :: Linux
Classifier: Programming Language :: Python :: 3.10
Classifier: Programming Language :: Python :: 3.11
Classifier: Programming Language :: Python :: 3.12
Classifier: Programming Language :: Python :: 3.13
Classifier: Programming Language :: Python :: 3.14
Classifier: Programming Language :: Python :: Implementation :: CPython
Classifier: Topic :: Software Development :: User Interfaces
Requires-Python: >=3.10
License-File: LICENSE.txt
Requires-Dist: numpy
Requires-Dist: Pillow
Requires-Dist: six
Dynamic: classifier
Dynamic: description
Dynamic: keywords
Dynamic: license
Dynamic: license-file
Dynamic: maintainer
Dynamic: maintainer-email
Dynamic: platform
Dynamic: requires-dist
Dynamic: requires-python
Dynamic: summary
